{
    "swagger": "2.0",
    "info": {
        "description": "API for KienlongBank Treasury Management System — Phase 1",
        "title": "Treasury Management System API",
        "termsOfService": "https://kienlongbank.com/terms",
        "contact": {
            "name": "KienlongBank IT Department",
            "email": "it@kienlongbank.com"
        },
        "license": {
            "name": "Proprietary",
            "url": "https://kienlongbank.com/license"
        },
        "version": "1.0"
    },
    "host": "localhost:34000",
    "basePath": "/api/v1",
    "paths": {
        "/fx": {
            "get": {
                "security": [
                    {
                        "BearerAuth": []
                    }
                ],
                "description": "Lấy danh sách giao dịch ngoại tệ với filter và phân trang. Dữ liệu được lọc theo quyền của người dùng (BRD v3 §6.2).",
                "consumes": [
                    "application/json"
                ],
                "produces": [
                    "application/json"
                ],
                "tags": [
                    "FX"
                ],
                "summary": "Danh sách giao dịch FX",
                "parameters": [
                    {
                        "type": "string",
                        "description": "Filter by status (OPEN, PENDING_L2_APPROVAL, ...)",
                        "name": "status",
                        "in": "query"
                    },
                    {
                        "type": "string",
                        "description": "Filter by type (SPOT, FORWARD, SWAP)",
                        "name": "deal_type",
                        "in": "query"
                    },
                    {
                        "type": "string",
                        "description": "Filter by counterparty UUID",
                        "name": "counterparty_id",
                        "in": "query"
                    },
                    {
                        "type": "string",
                        "description": "From date (YYYY-MM-DD)",
                        "name": "from_date",
                        "in": "query"
                    },
                    {
                        "type": "string",
                        "description": "To date (YYYY-MM-DD)",
                        "name": "to_date",
                        "in": "query"
                    },
                    {
                        "type": "string",
                        "description": "Filter by ticket number",
                        "name": "ticket_number",
                        "in": "query"
                    },
                    {
                        "type": "integer",
                        "default": 1,
                        "description": "Page number (offset mode)",
                        "name": "page",
                        "in": "query"
                    },
                    {
                        "type": "integer",
                        "default": 20,
                        "description": "Items per page",
                        "name": "page_size",
                        "in": "query"
                    },
                    {
                        "type": "string",
                        "default": "created_at",
                        "description": "Sort field",
                        "name": "sort_by",
                        "in": "query"
                    },
                    {
                        "type": "string",
                        "default": "desc",
                        "description": "Sort direction (asc, desc)",
                        "name": "sort_dir",
                        "in": "query"
                    },
                    {
                        "type": "string",
                        "description": "Cursor for keyset pagination",
                        "name": "cursor",
                        "in": "query"
                    },
                    {
                        "type": "integer",
                        "default": 20,
                        "description": "Limit for cursor mode",
                        "name": "limit",
                        "in": "query"
                    },
                    {
                        "type": "string",
                        "description": "Cursor direction (next, prev)",
                        "name": "direction",
                        "in": "query"
                    }
                ],
                "responses": {
                    "200": {
                        "description": "OK",
                        "schema": {
                            "allOf": [
                                {
                                    "$ref": "#/definitions/github_com_kienlongbank_treasury-api_pkg_dto.APIResponse"
                                },
                                {
                                    "type": "object",
                                    "properties": {
                                        "data": {
                                            "type": "array",
                                            "items": {
                                                "$ref": "#/definitions/github_com_kienlongbank_treasury-api_pkg_dto.FxDealResponse"
                                            }
                                        },
                                        "meta": {
                                            "$ref": "#/definitions/github_com_kienlongbank_treasury-api_pkg_dto.ResponseMeta"
                                        }
                                    }
                                }
                            ]
                        }
                    },
                    "401": {
                        "description": "Unauthorized",
                        "schema": {
                            "allOf": [
                                {
                                    "$ref": "#/definitions/github_com_kienlongbank_treasury-api_pkg_dto.APIResponse"
                                },
                                {
                                    "type": "object",
                                    "properties": {
                                        "error": {
                                            "$ref": "#/definitions/github_com_kienlongbank_treasury-api_pkg_dto.APIError"
                                        }
                                    }
                                }
                            ]
                        }
                    },
                    "403": {
                        "description": "Forbidden",
                        "schema": {
                            "allOf": [
                                {
                                    "$ref": "#/definitions/github_com_kienlongbank_treasury-api_pkg_dto.APIResponse"
                                },
                                {
                                    "type": "object",
                                    "properties": {
                                        "error": {
                                            "$ref": "#/definitions/github_com_kienlongbank_treasury-api_pkg_dto.APIError"
                                        }
                                    }
                                }
                            ]
                        }
                    },
                    "500": {
                        "description": "Internal Server Error",
                        "schema": {
                            "allOf": [
                                {
                                    "$ref": "#/definitions/github_com_kienlongbank_treasury-api_pkg_dto.APIResponse"
                                },
                                {
                                    "type": "object",
                                    "properties": {
                                        "error": {
                                            "$ref": "#/definitions/github_com_kienlongbank_treasury-api_pkg_dto.APIError"
                                        }
                                    }
                                }
                            ]
                        }
                    }
                }
            },
            "post": {
                "security": [
                    {
                        "BearerAuth": []
                    }
                ],
                "description": "Tạo một giao dịch ngoại tệ mới (Spot, Forward, hoặc Swap). Giao dịch được tạo ở trạng thái OPEN.",
                "consumes": [
                    "application/json"
                ],
                "produces": [
                    "application/json"
                ],
                "tags": [
                    "FX"
                ],
                "summary": "Tạo giao dịch FX mới",
                "parameters": [
                    {
                        "description": "FX deal creation payload",
                        "name": "body",
                        "in": "body",
                        "required": true,
                        "schema": {
                            "$ref": "#/definitions/github_com_kienlongbank_treasury-api_pkg_dto.CreateFxDealRequest"
                        }
                    }
                ],
                "responses": {
                    "201": {
                        "description": "Created",
                        "schema": {
                            "allOf": [
                                {
                                    "$ref": "#/definitions/github_com_kienlongbank_treasury-api_pkg_dto.APIResponse"
                                },
                                {
                                    "type": "object",
                                    "properties": {
                                        "data": {
                                            "$ref": "#/definitions/github_com_kienlongbank_treasury-api_pkg_dto.FxDealResponse"
                                        },
                                        "meta": {
                                            "$ref": "#/definitions/github_com_kienlongbank_treasury-api_pkg_dto.ResponseMeta"
                                        }
                                    }
                                }
                            ]
                        }
                    },
                    "400": {
                        "description": "Bad Request",
                        "schema": {
                            "allOf": [
                                {
                                    "$ref": "#/definitions/github_com_kienlongbank_treasury-api_pkg_dto.APIResponse"
                                },
                                {
                                    "type": "object",
                                    "properties": {
                                        "error": {
                                            "$ref": "#/definitions/github_com_kienlongbank_treasury-api_pkg_dto.APIError"
                                        }
                                    }
                                }
                            ]
                        }
                    },
                    "401": {
                        "description": "Unauthorized",
                        "schema": {
                            "allOf": [
                                {
                                    "$ref": "#/definitions/github_com_kienlongbank_treasury-api_pkg_dto.APIResponse"
                                },
                                {
                                    "type": "object",
                                    "properties": {
                                        "error": {
                                            "$ref": "#/definitions/github_com_kienlongbank_treasury-api_pkg_dto.APIError"
                                        }
                                    }
                                }
                            ]
                        }
                    },
                    "403": {
                        "description": "Forbidden",
                        "schema": {
                            "allOf": [
                                {
                                    "$ref": "#/definitions/github_com_kienlongbank_treasury-api_pkg_dto.APIResponse"
                                },
                                {
                                    "type": "object",
                                    "properties": {
                                        "error": {
                                            "$ref": "#/definitions/github_com_kienlongbank_treasury-api_pkg_dto.APIError"
                                        }
                                    }
                                }
                            ]
                        }
                    },
                    "500": {
                        "description": "Internal Server Error",
                        "schema": {
                            "allOf": [
                                {
                                    "$ref": "#/definitions/github_com_kienlongbank_treasury-api_pkg_dto.APIResponse"
                                },
                                {
                                    "type": "object",
                                    "properties": {
                                        "error": {
                                            "$ref": "#/definitions/github_com_kienlongbank_treasury-api_pkg_dto.APIError"
                                        }
                                    }
                                }
                            ]
                        }
                    }
                }
            }
        },
        "/fx/{id}": {
            "get": {
                "security": [
                    {
                        "BearerAuth": []
                    }
                ],
                "description": "Lấy thông tin chi tiết một giao dịch ngoại tệ theo ID.",
                "consumes": [
                    "application/json"
                ],
                "produces": [
                    "application/json"
                ],
                "tags": [
                    "FX"
                ],
                "summary": "Chi tiết giao dịch FX",
                "parameters": [
                    {
                        "type": "string",
                        "description": "FX Deal ID (UUID)",
                        "name": "id",
                        "in": "path",
                        "required": true
                    }
                ],
                "responses": {
                    "200": {
                        "description": "OK",
                        "schema": {
                            "allOf": [
                                {
                                    "$ref": "#/definitions/github_com_kienlongbank_treasury-api_pkg_dto.APIResponse"
                                },
                                {
                                    "type": "object",
                                    "properties": {
                                        "data": {
                                            "$ref": "#/definitions/github_com_kienlongbank_treasury-api_pkg_dto.FxDealResponse"
                                        },
                                        "meta": {
                                            "$ref": "#/definitions/github_com_kienlongbank_treasury-api_pkg_dto.ResponseMeta"
                                        }
                                    }
                                }
                            ]
                        }
                    },
                    "400": {
                        "description": "Bad Request",
                        "schema": {
                            "allOf": [
                                {
                                    "$ref": "#/definitions/github_com_kienlongbank_treasury-api_pkg_dto.APIResponse"
                                },
                                {
                                    "type": "object",
                                    "properties": {
                                        "error": {
                                            "$ref": "#/definitions/github_com_kienlongbank_treasury-api_pkg_dto.APIError"
                                        }
                                    }
                                }
                            ]
                        }
                    },
                    "401": {
                        "description": "Unauthorized",
                        "schema": {
                            "allOf": [
                                {
                                    "$ref": "#/definitions/github_com_kienlongbank_treasury-api_pkg_dto.APIResponse"
                                },
                                {
                                    "type": "object",
                                    "properties": {
                                        "error": {
                                            "$ref": "#/definitions/github_com_kienlongbank_treasury-api_pkg_dto.APIError"
                                        }
                                    }
                                }
                            ]
                        }
                    },
                    "403": {
                        "description": "Forbidden",
                        "schema": {
                            "allOf": [
                                {
                                    "$ref": "#/definitions/github_com_kienlongbank_treasury-api_pkg_dto.APIResponse"
                                },
                                {
                                    "type": "object",
                                    "properties": {
                                        "error": {
                                            "$ref": "#/definitions/github_com_kienlongbank_treasury-api_pkg_dto.APIError"
                                        }
                                    }
                                }
                            ]
                        }
                    },
                    "404": {
                        "description": "Not Found",
                        "schema": {
                            "allOf": [
                                {
                                    "$ref": "#/definitions/github_com_kienlongbank_treasury-api_pkg_dto.APIResponse"
                                },
                                {
                                    "type": "object",
                                    "properties": {
                                        "error": {
                                            "$ref": "#/definitions/github_com_kienlongbank_treasury-api_pkg_dto.APIError"
                                        }
                                    }
                                }
                            ]
                        }
                    },
                    "500": {
                        "description": "Internal Server Error",
                        "schema": {
                            "allOf": [
                                {
                                    "$ref": "#/definitions/github_com_kienlongbank_treasury-api_pkg_dto.APIResponse"
                                },
                                {
                                    "type": "object",
                                    "properties": {
                                        "error": {
                                            "$ref": "#/definitions/github_com_kienlongbank_treasury-api_pkg_dto.APIError"
                                        }
                                    }
                                }
                            ]
                        }
                    }
                }
            },
            "put": {
                "security": [
                    {
                        "BearerAuth": []
                    }
                ],
                "description": "Cập nhật thông tin giao dịch ngoại tệ. Chỉ giao dịch ở trạng thái OPEN mới được sửa. Sử dụng optimistic locking (version).",
                "consumes": [
                    "application/json"
                ],
                "produces": [
                    "application/json"
                ],
                "tags": [
                    "FX"
                ],
                "summary": "Cập nhật giao dịch FX",
                "parameters": [
                    {
                        "type": "string",
                        "description": "FX Deal ID (UUID)",
                        "name": "id",
                        "in": "path",
                        "required": true
                    },
                    {
                        "description": "FX deal update payload",
                        "name": "body",
                        "in": "body",
                        "required": true,
                        "schema": {
                            "$ref": "#/definitions/github_com_kienlongbank_treasury-api_pkg_dto.UpdateFxDealRequest"
                        }
                    }
                ],
                "responses": {
                    "200": {
                        "description": "OK",
                        "schema": {
                            "allOf": [
                                {
                                    "$ref": "#/definitions/github_com_kienlongbank_treasury-api_pkg_dto.APIResponse"
                                },
                                {
                                    "type": "object",
                                    "properties": {
                                        "data": {
                                            "$ref": "#/definitions/github_com_kienlongbank_treasury-api_pkg_dto.FxDealResponse"
                                        },
                                        "meta": {
                                            "$ref": "#/definitions/github_com_kienlongbank_treasury-api_pkg_dto.ResponseMeta"
                                        }
                                    }
                                }
                            ]
                        }
                    },
                    "400": {
                        "description": "Bad Request",
                        "schema": {
                            "allOf": [
                                {
                                    "$ref": "#/definitions/github_com_kienlongbank_treasury-api_pkg_dto.APIResponse"
                                },
                                {
                                    "type": "object",
                                    "properties": {
                                        "error": {
                                            "$ref": "#/definitions/github_com_kienlongbank_treasury-api_pkg_dto.APIError"
                                        }
                                    }
                                }
                            ]
                        }
                    },
                    "401": {
                        "description": "Unauthorized",
                        "schema": {
                            "allOf": [
                                {
                                    "$ref": "#/definitions/github_com_kienlongbank_treasury-api_pkg_dto.APIResponse"
                                },
                                {
                                    "type": "object",
                                    "properties": {
                                        "error": {
                                            "$ref": "#/definitions/github_com_kienlongbank_treasury-api_pkg_dto.APIError"
                                        }
                                    }
                                }
                            ]
                        }
                    },
                    "403": {
                        "description": "Forbidden",
                        "schema": {
                            "allOf": [
                                {
                                    "$ref": "#/definitions/github_com_kienlongbank_treasury-api_pkg_dto.APIResponse"
                                },
                                {
                                    "type": "object",
                                    "properties": {
                                        "error": {
                                            "$ref": "#/definitions/github_com_kienlongbank_treasury-api_pkg_dto.APIError"
                                        }
                                    }
                                }
                            ]
                        }
                    },
                    "404": {
                        "description": "Not Found",
                        "schema": {
                            "allOf": [
                                {
                                    "$ref": "#/definitions/github_com_kienlongbank_treasury-api_pkg_dto.APIResponse"
                                },
                                {
                                    "type": "object",
                                    "properties": {
                                        "error": {
                                            "$ref": "#/definitions/github_com_kienlongbank_treasury-api_pkg_dto.APIError"
                                        }
                                    }
                                }
                            ]
                        }
                    },
                    "409": {
                        "description": "Conflict",
                        "schema": {
                            "allOf": [
                                {
                                    "$ref": "#/definitions/github_com_kienlongbank_treasury-api_pkg_dto.APIResponse"
                                },
                                {
                                    "type": "object",
                                    "properties": {
                                        "error": {
                                            "$ref": "#/definitions/github_com_kienlongbank_treasury-api_pkg_dto.APIError"
                                        }
                                    }
                                }
                            ]
                        }
                    },
                    "500": {
                        "description": "Internal Server Error",
                        "schema": {
                            "allOf": [
                                {
                                    "$ref": "#/definitions/github_com_kienlongbank_treasury-api_pkg_dto.APIResponse"
                                },
                                {
                                    "type": "object",
                                    "properties": {
                                        "error": {
                                            "$ref": "#/definitions/github_com_kienlongbank_treasury-api_pkg_dto.APIError"
                                        }
                                    }
                                }
                            ]
                        }
                    }
                }
            },
            "delete": {
                "security": [
                    {
                        "BearerAuth": []
                    }
                ],
                "description": "Xóa mềm (soft delete) giao dịch ngoại tệ. Giao dịch vẫn tồn tại trong DB nhưng không hiển thị.",
                "consumes": [
                    "application/json"
                ],
                "produces": [
                    "application/json"
                ],
                "tags": [
                    "FX"
                ],
                "summary": "Xóa mềm giao dịch FX",
                "parameters": [
                    {
                        "type": "string",
                        "description": "FX Deal ID (UUID)",
                        "name": "id",
                        "in": "path",
                        "required": true
                    }
                ],
                "responses": {
                    "204": {
                        "description": "No Content"
                    },
                    "400": {
                        "description": "Bad Request",
                        "schema": {
                            "allOf": [
                                {
                                    "$ref": "#/definitions/github_com_kienlongbank_treasury-api_pkg_dto.APIResponse"
                                },
                                {
                                    "type": "object",
                                    "properties": {
                                        "error": {
                                            "$ref": "#/definitions/github_com_kienlongbank_treasury-api_pkg_dto.APIError"
                                        }
                                    }
                                }
                            ]
                        }
                    },
                    "401": {
                        "description": "Unauthorized",
                        "schema": {
                            "allOf": [
                                {
                                    "$ref": "#/definitions/github_com_kienlongbank_treasury-api_pkg_dto.APIResponse"
                                },
                                {
                                    "type": "object",
                                    "properties": {
                                        "error": {
                                            "$ref": "#/definitions/github_com_kienlongbank_treasury-api_pkg_dto.APIError"
                                        }
                                    }
                                }
                            ]
                        }
                    },
                    "403": {
                        "description": "Forbidden",
                        "schema": {
                            "allOf": [
                                {
                                    "$ref": "#/definitions/github_com_kienlongbank_treasury-api_pkg_dto.APIResponse"
                                },
                                {
                                    "type": "object",
                                    "properties": {
                                        "error": {
                                            "$ref": "#/definitions/github_com_kienlongbank_treasury-api_pkg_dto.APIError"
                                        }
                                    }
                                }
                            ]
                        }
                    },
                    "404": {
                        "description": "Not Found",
                        "schema": {
                            "allOf": [
                                {
                                    "$ref": "#/definitions/github_com_kienlongbank_treasury-api_pkg_dto.APIResponse"
                                },
                                {
                                    "type": "object",
                                    "properties": {
                                        "error": {
                                            "$ref": "#/definitions/github_com_kienlongbank_treasury-api_pkg_dto.APIError"
                                        }
                                    }
                                }
                            ]
                        }
                    },
                    "500": {
                        "description": "Internal Server Error",
                        "schema": {
                            "allOf": [
                                {
                                    "$ref": "#/definitions/github_com_kienlongbank_treasury-api_pkg_dto.APIResponse"
                                },
                                {
                                    "type": "object",
                                    "properties": {
                                        "error": {
                                            "$ref": "#/definitions/github_com_kienlongbank_treasury-api_pkg_dto.APIError"
                                        }
                                    }
                                }
                            ]
                        }
                    }
                }
            }
        },
        "/fx/{id}/approve": {
            "post": {
                "security": [
                    {
                        "BearerAuth": []
                    }
                ],
                "description": "Phê duyệt (APPROVE) hoặc từ chối (REJECT) giao dịch ngoại tệ. Yêu cầu quyền FX_DEAL.APPROVE.",
                "consumes": [
                    "application/json"
                ],
                "produces": [
                    "application/json"
                ],
                "tags": [
                    "FX"
                ],
                "summary": "Phê duyệt / Từ chối giao dịch FX",
                "parameters": [
                    {
                        "type": "string",
                        "description": "FX Deal ID (UUID)",
                        "name": "id",
                        "in": "path",
                        "required": true
                    },
                    {
                        "description": "Approval payload",
                        "name": "body",
                        "in": "body",
                        "required": true,
                        "schema": {
                            "$ref": "#/definitions/github_com_kienlongbank_treasury-api_pkg_dto.ApprovalRequest"
                        }
                    }
                ],
                "responses": {
                    "200": {
                        "description": "OK",
                        "schema": {
                            "allOf": [
                                {
                                    "$ref": "#/definitions/github_com_kienlongbank_treasury-api_pkg_dto.APIResponse"
                                },
                                {
                                    "type": "object",
                                    "properties": {
                                        "data": {
                                            "type": "object"
                                        },
                                        "meta": {
                                            "$ref": "#/definitions/github_com_kienlongbank_treasury-api_pkg_dto.ResponseMeta"
                                        }
                                    }
                                }
                            ]
                        }
                    },
                    "400": {
                        "description": "Bad Request",
                        "schema": {
                            "allOf": [
                                {
                                    "$ref": "#/definitions/github_com_kienlongbank_treasury-api_pkg_dto.APIResponse"
                                },
                                {
                                    "type": "object",
                                    "properties": {
                                        "error": {
                                            "$ref": "#/definitions/github_com_kienlongbank_treasury-api_pkg_dto.APIError"
                                        }
                                    }
                                }
                            ]
                        }
                    },
                    "401": {
                        "description": "Unauthorized",
                        "schema": {
                            "allOf": [
                                {
                                    "$ref": "#/definitions/github_com_kienlongbank_treasury-api_pkg_dto.APIResponse"
                                },
                                {
                                    "type": "object",
                                    "properties": {
                                        "error": {
                                            "$ref": "#/definitions/github_com_kienlongbank_treasury-api_pkg_dto.APIError"
                                        }
                                    }
                                }
                            ]
                        }
                    },
                    "403": {
                        "description": "Forbidden",
                        "schema": {
                            "allOf": [
                                {
                                    "$ref": "#/definitions/github_com_kienlongbank_treasury-api_pkg_dto.APIResponse"
                                },
                                {
                                    "type": "object",
                                    "properties": {
                                        "error": {
                                            "$ref": "#/definitions/github_com_kienlongbank_treasury-api_pkg_dto.APIError"
                                        }
                                    }
                                }
                            ]
                        }
                    },
                    "404": {
                        "description": "Not Found",
                        "schema": {
                            "allOf": [
                                {
                                    "$ref": "#/definitions/github_com_kienlongbank_treasury-api_pkg_dto.APIResponse"
                                },
                                {
                                    "type": "object",
                                    "properties": {
                                        "error": {
                                            "$ref": "#/definitions/github_com_kienlongbank_treasury-api_pkg_dto.APIError"
                                        }
                                    }
                                }
                            ]
                        }
                    },
                    "409": {
                        "description": "Conflict",
                        "schema": {
                            "allOf": [
                                {
                                    "$ref": "#/definitions/github_com_kienlongbank_treasury-api_pkg_dto.APIResponse"
                                },
                                {
                                    "type": "object",
                                    "properties": {
                                        "error": {
                                            "$ref": "#/definitions/github_com_kienlongbank_treasury-api_pkg_dto.APIError"
                                        }
                                    }
                                }
                            ]
                        }
                    },
                    "500": {
                        "description": "Internal Server Error",
                        "schema": {
                            "allOf": [
                                {
                                    "$ref": "#/definitions/github_com_kienlongbank_treasury-api_pkg_dto.APIResponse"
                                },
                                {
                                    "type": "object",
                                    "properties": {
                                        "error": {
                                            "$ref": "#/definitions/github_com_kienlongbank_treasury-api_pkg_dto.APIError"
                                        }
                                    }
                                }
                            ]
                        }
                    }
                }
            }
        },
        "/fx/{id}/cancel": {
            "post": {
                "security": [
                    {
                        "BearerAuth": []
                    }
                ],
                "description": "Yêu cầu hủy giao dịch ngoại tệ. Giao dịch sẽ chuyển sang trạng thái CANCELLED.",
                "consumes": [
                    "application/json"
                ],
                "produces": [
                    "application/json"
                ],
                "tags": [
                    "FX"
                ],
                "summary": "Hủy giao dịch FX",
                "parameters": [
                    {
                        "type": "string",
                        "description": "FX Deal ID (UUID)",
                        "name": "id",
                        "in": "path",
                        "required": true
                    },
                    {
                        "description": "Cancellation reason",
                        "name": "body",
                        "in": "body",
                        "required": true,
                        "schema": {
                            "type": "object",
                            "properties": {
                                "reason": {
                                    "type": "string"
                                }
                            }
                        }
                    }
                ],
                "responses": {
                    "200": {
                        "description": "OK",
                        "schema": {
                            "allOf": [
                                {
                                    "$ref": "#/definitions/github_com_kienlongbank_treasury-api_pkg_dto.APIResponse"
                                },
                                {
                                    "type": "object",
                                    "properties": {
                                        "data": {
                                            "type": "object"
                                        },
                                        "meta": {
                                            "$ref": "#/definitions/github_com_kienlongbank_treasury-api_pkg_dto.ResponseMeta"
                                        }
                                    }
                                }
                            ]
                        }
                    },
                    "400": {
                        "description": "Bad Request",
                        "schema": {
                            "allOf": [
                                {
                                    "$ref": "#/definitions/github_com_kienlongbank_treasury-api_pkg_dto.APIResponse"
                                },
                                {
                                    "type": "object",
                                    "properties": {
                                        "error": {
                                            "$ref": "#/definitions/github_com_kienlongbank_treasury-api_pkg_dto.APIError"
                                        }
                                    }
                                }
                            ]
                        }
                    },
                    "401": {
                        "description": "Unauthorized",
                        "schema": {
                            "allOf": [
                                {
                                    "$ref": "#/definitions/github_com_kienlongbank_treasury-api_pkg_dto.APIResponse"
                                },
                                {
                                    "type": "object",
                                    "properties": {
                                        "error": {
                                            "$ref": "#/definitions/github_com_kienlongbank_treasury-api_pkg_dto.APIError"
                                        }
                                    }
                                }
                            ]
                        }
                    },
                    "403": {
                        "description": "Forbidden",
                        "schema": {
                            "allOf": [
                                {
                                    "$ref": "#/definitions/github_com_kienlongbank_treasury-api_pkg_dto.APIResponse"
                                },
                                {
                                    "type": "object",
                                    "properties": {
                                        "error": {
                                            "$ref": "#/definitions/github_com_kienlongbank_treasury-api_pkg_dto.APIError"
                                        }
                                    }
                                }
                            ]
                        }
                    },
                    "404": {
                        "description": "Not Found",
                        "schema": {
                            "allOf": [
                                {
                                    "$ref": "#/definitions/github_com_kienlongbank_treasury-api_pkg_dto.APIResponse"
                                },
                                {
                                    "type": "object",
                                    "properties": {
                                        "error": {
                                            "$ref": "#/definitions/github_com_kienlongbank_treasury-api_pkg_dto.APIError"
                                        }
                                    }
                                }
                            ]
                        }
                    },
                    "409": {
                        "description": "Conflict",
                        "schema": {
                            "allOf": [
                                {
                                    "$ref": "#/definitions/github_com_kienlongbank_treasury-api_pkg_dto.APIResponse"
                                },
                                {
                                    "type": "object",
                                    "properties": {
                                        "error": {
                                            "$ref": "#/definitions/github_com_kienlongbank_treasury-api_pkg_dto.APIError"
                                        }
                                    }
                                }
                            ]
                        }
                    },
                    "500": {
                        "description": "Internal Server Error",
                        "schema": {
                            "allOf": [
                                {
                                    "$ref": "#/definitions/github_com_kienlongbank_treasury-api_pkg_dto.APIResponse"
                                },
                                {
                                    "type": "object",
                                    "properties": {
                                        "error": {
                                            "$ref": "#/definitions/github_com_kienlongbank_treasury-api_pkg_dto.APIError"
                                        }
                                    }
                                }
                            ]
                        }
                    }
                }
            }
        },
        "/fx/{id}/clone": {
            "post": {
                "security": [
                    {
                        "BearerAuth": []
                    }
                ],
                "description": "Tạo bản sao của giao dịch ngoại tệ hiện có. Giao dịch mới ở trạng thái OPEN.",
                "consumes": [
                    "application/json"
                ],
                "produces": [
                    "application/json"
                ],
                "tags": [
                    "FX"
                ],
                "summary": "Sao chép giao dịch FX",
                "parameters": [
                    {
                        "type": "string",
                        "description": "FX Deal ID to clone (UUID)",
                        "name": "id",
                        "in": "path",
                        "required": true
                    }
                ],
                "responses": {
                    "201": {
                        "description": "Created",
                        "schema": {
                            "allOf": [
                                {
                                    "$ref": "#/definitions/github_com_kienlongbank_treasury-api_pkg_dto.APIResponse"
                                },
                                {
                                    "type": "object",
                                    "properties": {
                                        "data": {
                                            "$ref": "#/definitions/github_com_kienlongbank_treasury-api_pkg_dto.FxDealResponse"
                                        },
                                        "meta": {
                                            "$ref": "#/definitions/github_com_kienlongbank_treasury-api_pkg_dto.ResponseMeta"
                                        }
                                    }
                                }
                            ]
                        }
                    },
                    "400": {
                        "description": "Bad Request",
                        "schema": {
                            "allOf": [
                                {
                                    "$ref": "#/definitions/github_com_kienlongbank_treasury-api_pkg_dto.APIResponse"
                                },
                                {
                                    "type": "object",
                                    "properties": {
                                        "error": {
                                            "$ref": "#/definitions/github_com_kienlongbank_treasury-api_pkg_dto.APIError"
                                        }
                                    }
                                }
                            ]
                        }
                    },
                    "401": {
                        "description": "Unauthorized",
                        "schema": {
                            "allOf": [
                                {
                                    "$ref": "#/definitions/github_com_kienlongbank_treasury-api_pkg_dto.APIResponse"
                                },
                                {
                                    "type": "object",
                                    "properties": {
                                        "error": {
                                            "$ref": "#/definitions/github_com_kienlongbank_treasury-api_pkg_dto.APIError"
                                        }
                                    }
                                }
                            ]
                        }
                    },
                    "403": {
                        "description": "Forbidden",
                        "schema": {
                            "allOf": [
                                {
                                    "$ref": "#/definitions/github_com_kienlongbank_treasury-api_pkg_dto.APIResponse"
                                },
                                {
                                    "type": "object",
                                    "properties": {
                                        "error": {
                                            "$ref": "#/definitions/github_com_kienlongbank_treasury-api_pkg_dto.APIError"
                                        }
                                    }
                                }
                            ]
                        }
                    },
                    "404": {
                        "description": "Not Found",
                        "schema": {
                            "allOf": [
                                {
                                    "$ref": "#/definitions/github_com_kienlongbank_treasury-api_pkg_dto.APIResponse"
                                },
                                {
                                    "type": "object",
                                    "properties": {
                                        "error": {
                                            "$ref": "#/definitions/github_com_kienlongbank_treasury-api_pkg_dto.APIError"
                                        }
                                    }
                                }
                            ]
                        }
                    },
                    "500": {
                        "description": "Internal Server Error",
                        "schema": {
                            "allOf": [
                                {
                                    "$ref": "#/definitions/github_com_kienlongbank_treasury-api_pkg_dto.APIResponse"
                                },
                                {
                                    "type": "object",
                                    "properties": {
                                        "error": {
                                            "$ref": "#/definitions/github_com_kienlongbank_treasury-api_pkg_dto.APIError"
                                        }
                                    }
                                }
                            ]
                        }
                    }
                }
            }
        },
        "/fx/{id}/recall": {
            "post": {
                "security": [
                    {
                        "BearerAuth": []
                    }
                ],
                "description": "Thu hồi giao dịch ngoại tệ về trạng thái OPEN (khi đang chờ duyệt). Yêu cầu quyền FX_DEAL.RECALL.",
                "consumes": [
                    "application/json"
                ],
                "produces": [
                    "application/json"
                ],
                "tags": [
                    "FX"
                ],
                "summary": "Thu hồi giao dịch FX",
                "parameters": [
                    {
                        "type": "string",
                        "description": "FX Deal ID (UUID)",
                        "name": "id",
                        "in": "path",
                        "required": true
                    },
                    {
                        "description": "Recall reason",
                        "name": "body",
                        "in": "body",
                        "required": true,
                        "schema": {
                            "type": "object",
                            "properties": {
                                "reason": {
                                    "type": "string"
                                }
                            }
                        }
                    }
                ],
                "responses": {
                    "200": {
                        "description": "OK",
                        "schema": {
                            "allOf": [
                                {
                                    "$ref": "#/definitions/github_com_kienlongbank_treasury-api_pkg_dto.APIResponse"
                                },
                                {
                                    "type": "object",
                                    "properties": {
                                        "data": {
                                            "type": "object"
                                        },
                                        "meta": {
                                            "$ref": "#/definitions/github_com_kienlongbank_treasury-api_pkg_dto.ResponseMeta"
                                        }
                                    }
                                }
                            ]
                        }
                    },
                    "400": {
                        "description": "Bad Request",
                        "schema": {
                            "allOf": [
                                {
                                    "$ref": "#/definitions/github_com_kienlongbank_treasury-api_pkg_dto.APIResponse"
                                },
                                {
                                    "type": "object",
                                    "properties": {
                                        "error": {
                                            "$ref": "#/definitions/github_com_kienlongbank_treasury-api_pkg_dto.APIError"
                                        }
                                    }
                                }
                            ]
                        }
                    },
                    "401": {
                        "description": "Unauthorized",
                        "schema": {
                            "allOf": [
                                {
                                    "$ref": "#/definitions/github_com_kienlongbank_treasury-api_pkg_dto.APIResponse"
                                },
                                {
                                    "type": "object",
                                    "properties": {
                                        "error": {
                                            "$ref": "#/definitions/github_com_kienlongbank_treasury-api_pkg_dto.APIError"
                                        }
                                    }
                                }
                            ]
                        }
                    },
                    "403": {
                        "description": "Forbidden",
                        "schema": {
                            "allOf": [
                                {
                                    "$ref": "#/definitions/github_com_kienlongbank_treasury-api_pkg_dto.APIResponse"
                                },
                                {
                                    "type": "object",
                                    "properties": {
                                        "error": {
                                            "$ref": "#/definitions/github_com_kienlongbank_treasury-api_pkg_dto.APIError"
                                        }
                                    }
                                }
                            ]
                        }
                    },
                    "404": {
                        "description": "Not Found",
                        "schema": {
                            "allOf": [
                                {
                                    "$ref": "#/definitions/github_com_kienlongbank_treasury-api_pkg_dto.APIResponse"
                                },
                                {
                                    "type": "object",
                                    "properties": {
                                        "error": {
                                            "$ref": "#/definitions/github_com_kienlongbank_treasury-api_pkg_dto.APIError"
                                        }
                                    }
                                }
                            ]
                        }
                    },
                    "409": {
                        "description": "Conflict",
                        "schema": {
                            "allOf": [
                                {
                                    "$ref": "#/definitions/github_com_kienlongbank_treasury-api_pkg_dto.APIResponse"
                                },
                                {
                                    "type": "object",
                                    "properties": {
                                        "error": {
                                            "$ref": "#/definitions/github_com_kienlongbank_treasury-api_pkg_dto.APIError"
                                        }
                                    }
                                }
                            ]
                        }
                    },
                    "500": {
                        "description": "Internal Server Error",
                        "schema": {
                            "allOf": [
                                {
                                    "$ref": "#/definitions/github_com_kienlongbank_treasury-api_pkg_dto.APIResponse"
                                },
                                {
                                    "type": "object",
                                    "properties": {
                                        "error": {
                                            "$ref": "#/definitions/github_com_kienlongbank_treasury-api_pkg_dto.APIError"
                                        }
                                    }
                                }
                            ]
                        }
                    }
                }
            }
        }
    },
    "definitions": {
        "github_com_kienlongbank_treasury-api_pkg_dto.APIError": {
            "description": "Standard error body with optional field-level validation errors.",
            "type": "object",
            "properties": {
                "code": {
                    "type": "string"
                },
                "detail": {
                    "type": "string"
                },
                "fields": {
                    "type": "object",
                    "additionalProperties": {
                        "type": "string"
                    }
                },
                "message": {
                    "type": "string"
                }
            }
        },
        "github_com_kienlongbank_treasury-api_pkg_dto.APIResponse": {
            "description": "Standard API response envelope.",
            "type": "object",
            "properties": {
                "data": {},
                "error": {
                    "$ref": "#/definitions/github_com_kienlongbank_treasury-api_pkg_dto.APIError"
                },
                "meta": {
                    "$ref": "#/definitions/github_com_kienlongbank_treasury-api_pkg_dto.ResponseMeta"
                },
                "success": {
                    "type": "boolean"
                }
            }
        },
        "github_com_kienlongbank_treasury-api_pkg_dto.ApprovalRequest": {
            "description": "Request body for deal approval or rejection.",
            "type": "object",
            "required": [
                "action",
                "version"
            ],
            "properties": {
                "action": {
                    "type": "string",
                    "enum": [
                        "APPROVE",
                        "REJECT"
                    ]
                },
                "comment": {
                    "type": "string",
                    "maxLength": 2000
                },
                "version": {
                    "type": "integer",
                    "minimum": 1
                }
            }
        },
        "github_com_kienlongbank_treasury-api_pkg_dto.CreateFxDealRequest": {
            "type": "object",
            "required": [
                "counterparty_id",
                "currency_code",
                "deal_type",
                "direction",
                "legs",
                "notional_amount",
                "trade_date"
            ],
            "properties": {
                "counterparty_id": {
                    "type": "string"
                },
                "currency_code": {
                    "type": "string"
                },
                "deal_type": {
                    "type": "string",
                    "enum": [
                        "SPOT",
                        "FORWARD",
                        "SWAP"
                    ]
                },
                "direction": {
                    "type": "string",
                    "enum": [
                        "SELL",
                        "BUY",
                        "SELL_BUY",
                        "BUY_SELL"
                    ]
                },
                "legs": {
                    "type": "array",
                    "maxItems": 2,
                    "minItems": 1,
                    "items": {
                        "$ref": "#/definitions/github_com_kienlongbank_treasury-api_pkg_dto.FxDealLegDTO"
                    }
                },
                "note": {
                    "type": "string",
                    "maxLength": 2000
                },
                "notional_amount": {
                    "type": "number"
                },
                "ticket_number": {
                    "type": "string",
                    "maxLength": 20
                },
                "trade_date": {
                    "type": "string"
                }
            }
        },
        "github_com_kienlongbank_treasury-api_pkg_dto.FxDealLegDTO": {
            "type": "object",
            "required": [
                "buy_amount",
                "buy_currency",
                "exchange_rate",
                "leg_number",
                "sell_amount",
                "sell_currency",
                "value_date"
            ],
            "properties": {
                "buy_amount": {
                    "type": "number"
                },
                "buy_currency": {
                    "type": "string"
                },
                "exchange_rate": {
                    "type": "number"
                },
                "leg_number": {
                    "type": "integer",
                    "maximum": 2,
                    "minimum": 1
                },
                "sell_amount": {
                    "type": "number"
                },
                "sell_currency": {
                    "type": "string"
                },
                "value_date": {
                    "type": "string"
                }
            }
        },
        "github_com_kienlongbank_treasury-api_pkg_dto.FxDealResponse": {
            "type": "object",
            "properties": {
                "counterparty_code": {
                    "type": "string"
                },
                "counterparty_id": {
                    "type": "string"
                },
                "counterparty_name": {
                    "type": "string"
                },
                "created_at": {
                    "type": "string"
                },
                "created_by": {
                    "type": "string"
                },
                "currency_code": {
                    "type": "string"
                },
                "deal_type": {
                    "type": "string"
                },
                "direction": {
                    "type": "string"
                },
                "id": {
                    "type": "string"
                },
                "legs": {
                    "type": "array",
                    "items": {
                        "$ref": "#/definitions/github_com_kienlongbank_treasury-api_pkg_dto.FxDealLegDTO"
                    }
                },
                "note": {
                    "type": "string"
                },
                "notional_amount": {
                    "type": "number"
                },
                "status": {
                    "type": "string"
                },
                "ticket_number": {
                    "type": "string"
                },
                "trade_date": {
                    "type": "string"
                },
                "updated_at": {
                    "type": "string"
                },
                "version": {
                    "type": "integer"
                }
            }
        },
        "github_com_kienlongbank_treasury-api_pkg_dto.PaginationMeta": {
            "description": "Pagination metadata for paginated responses.",
            "type": "object",
            "properties": {
                "has_more": {
                    "type": "boolean"
                },
                "next_cursor": {
                    "description": "Cursor mode",
                    "type": "string"
                },
                "page": {
                    "description": "Offset mode",
                    "type": "integer"
                },
                "page_size": {
                    "type": "integer"
                },
                "prev_cursor": {
                    "type": "string"
                },
                "total": {
                    "description": "Shared",
                    "type": "integer"
                },
                "total_pages": {
                    "type": "integer"
                }
            }
        },
        "github_com_kienlongbank_treasury-api_pkg_dto.ResponseMeta": {
            "description": "Metadata about the API response including request tracing and pagination.",
            "type": "object",
            "properties": {
                "pagination": {
                    "$ref": "#/definitions/github_com_kienlongbank_treasury-api_pkg_dto.PaginationMeta"
                },
                "request_id": {
                    "type": "string"
                },
                "timestamp": {
                    "type": "string"
                }
            }
        },
        "github_com_kienlongbank_treasury-api_pkg_dto.UpdateFxDealRequest": {
            "type": "object",
            "required": [
                "version"
            ],
            "properties": {
                "counterparty_id": {
                    "type": "string"
                },
                "currency_code": {
                    "type": "string"
                },
                "deal_type": {
                    "type": "string",
                    "enum": [
                        "SPOT",
                        "FORWARD",
                        "SWAP"
                    ]
                },
                "direction": {
                    "type": "string",
                    "enum": [
                        "SELL",
                        "BUY",
                        "SELL_BUY",
                        "BUY_SELL"
                    ]
                },
                "legs": {
                    "type": "array",
                    "maxItems": 2,
                    "minItems": 1,
                    "items": {
                        "$ref": "#/definitions/github_com_kienlongbank_treasury-api_pkg_dto.FxDealLegDTO"
                    }
                },
                "note": {
                    "type": "string",
                    "maxLength": 2000
                },
                "notional_amount": {
                    "type": "number"
                },
                "ticket_number": {
                    "type": "string",
                    "maxLength": 20
                },
                "trade_date": {
                    "type": "string"
                },
                "version": {
                    "description": "optimistic locking",
                    "type": "integer",
                    "minimum": 1
                }
            }
        }
    },
    "securityDefinitions": {
        "BearerAuth": {
            "description": "Bearer token (JWT)",
            "type": "apiKey",
            "name": "Authorization",
            "in": "header"
        }
    },
    "tags": [
        {
            "description": "Kinh doanh Ngoại tệ — Foreign Exchange (Spot, Forward, Swap)",
            "name": "FX"
        },
        {
            "description": "Giấy tờ có giá — Valuable Papers",
            "name": "GTCG"
        },
        {
            "description": "Thị trường Tiền tệ — Money Market",
            "name": "MM"
        },
        {
            "description": "Quản lý Hạn mức — Limit Management",
            "name": "Limits"
        },
        {
            "description": "Thanh toán Quốc tế — International Payment",
            "name": "TTQT"
        }
    ]
}